{
  "users": [
    {
      "id": 1,
      "email": "wfm@mail.ru",
      "password": "12345678",
      "firstName": "Иван",
      "lastName": "Пупкин",
      "phoneNumber": "053123123",
      "dateOfBirth": "12.09.2018",
      "maritalStatus": "Divorced",
      "gender": "male",
      "confession": "religious",
      "languages": [
        "Russian",
        "English"
      ],
      "foodPreferences": [
        "Kosher",
        "Vegetarian"
      ],
      "description": "I am cool guy",
      "pictureLink": [
        "path1",
        "path2"
      ],
      "banner": "pathBanner",
      "rate": 8.3,
      "numberOfVotes": 25
    },
    {
      "email": "test@mail",
      "password": "123123",
      "firstName": "Peter",
      "lastName": "Parker",
      "phoneNumber": 213,
      "dateOfBirth": "2019-01-09T22:00:00.000Z",
      "maritalStatus": "Married",
      "gender": "Male",
      "confession": "religious",
      "language": [
        "Hebrew",
        "English"
      ],
      "foodPreferences": [
        "Vegeterian"
      ],
      "description": "fvdsv",
      "pictureLink": [],
      "banner": "",
      "rate": 0,
      "numberOfVotes": 0,
      "id": 2
    }
  ],
  "events": [
    {
      "id": 1,
      "title": "Welcome",
      "holiday": "Pesah",
      "address": "Bar Kochva, 209",
      "confession": "religious",
      "dateFrom": "12.04.2019 19:00:00",
      "dateTo": "12.04.2019 23:00:00",
      "food": [
        "Kosher"
      ],
      "description": "We will eat and drink"
    }
  ]
}